{
  "transactions": [
    {
      "date": "2023-04-06",
      "description": "candy",
      "category": "food",
      "amount": "12",
      "type": "expense",
      "id": "000001"
    },
    {
      "date": "2023-04-06",
      "description": "vitamin",
      "category": "food",
      "amount": "13",
      "type": "expense",
      "id": "000010"
    },
    {
      "date": "2023-04-06",
      "description": "laptop",
      "category": "tech",
      "amount": "1000",
      "type": "expense",
      "id": "000011"
    },
    {
      "date": "4444-05-05",
      "description": "dftyh",
      "category": "dfth",
      "amount": 567,
      "type": "income",
      "id": "7c3bcb4a-8cab-4673-8e44-6d1d1d6113c3"
    },
    {
      "date": "7655-02-07",
      "description": "things",
      "category": "thingsss",
      "amount": 34534,
      "type": "income",
      "id": "aad9fc39-faf8-4642-8b0f-02ff20b0e040"
    }
  ]
}